pytest_never_sleep/__init__.py
pytest_never_sleep/_version.py
pytest_never_sleep/hooks.py
pytest_never_sleep/never_sleep.py
pytest_never_sleep/plugin.py
pytest_never_sleep-0.0.2.dist-info/LICENSE
pytest_never_sleep-0.0.2.dist-info/METADATA
pytest_never_sleep-0.0.2.dist-info/WHEEL
pytest_never_sleep-0.0.2.dist-info/entry_points.txt
pytest_never_sleep-0.0.2.dist-info/top_level.txt
pytest_never_sleep-0.0.2.dist-info/RECORD
